hangups/__init__.py
hangups/auth.py
hangups/channel.py
hangups/client.py
hangups/conversation.py
hangups/conversation_event.py
hangups/event.py
hangups/exceptions.py
hangups/googlechat_pb2.py
hangups/hangouts_pb2.py
hangups/http_utils.py
hangups/message_parser.py
hangups/parsers.py
hangups/pblite.py
hangups/user.py
hangups/version.py
hangups/ui/__init__.py
hangups/ui/__main__.py
hangups/ui/emoticon.py
hangups/ui/notifier.py
hangups/ui/utils.py
beeper_hangups-0.5.0a5.dist-info/LICENSE
beeper_hangups-0.5.0a5.dist-info/METADATA
beeper_hangups-0.5.0a5.dist-info/WHEEL
beeper_hangups-0.5.0a5.dist-info/entry_points.txt
beeper_hangups-0.5.0a5.dist-info/top_level.txt
beeper_hangups-0.5.0a5.dist-info/RECORD
