Metadata-Version: 2.1
Name: beeper-hangups
Version: 0.5.0a5
Summary: the first third-party instant messaging client for Google Hangouts
Home-page: https://github.com/beeper/hangups
Author: Tom Dryer
Author-email: tomdryer.com@gmail.com
License: MIT
Platform: UNKNOWN
Classifier: Development Status :: 3 - Alpha
Classifier: Intended Audience :: Developers
Classifier: Intended Audience :: End Users/Desktop
Classifier: Natural Language :: English
Classifier: License :: OSI Approved :: MIT License
Classifier: Programming Language :: Python :: 3 :: Only
Classifier: Programming Language :: Python :: 3.6
Classifier: Programming Language :: Python :: 3.7
Classifier: Programming Language :: Python :: 3.8
Classifier: Programming Language :: Python :: 3.9
Classifier: Topic :: Communications :: Chat
Classifier: Environment :: Console :: Curses
Requires-Dist: ReParser (==1.4.3)
Requires-Dist: aiohttp (<4,>=3.7)
Requires-Dist: appdirs (<1.5,>=1.4)
Requires-Dist: async-timeout (<4,>=2)
Requires-Dist: protobuf (<3.17,>=3.1.0)
Provides-Extra: dev
Requires-Dist: aiohttp-socks (<0.7,>=0.6) ; extra == 'dev'
Provides-Extra: ui
Requires-Dist: ConfigArgParse (<2,>=0.11.0) ; extra == 'ui'
Requires-Dist: readlike (<0.2,>=0.1.2) ; extra == 'ui'
Requires-Dist: urwid (<2.2,>=1.3.1) ; extra == 'ui'
